README.txt
setup.py
tgmigrate/__init__.py
tgmigrate/command.py
tgmigrate/release.py
tgmigrate.egg-info/PKG-INFO
tgmigrate.egg-info/SOURCES.txt
tgmigrate.egg-info/dependency_links.txt
tgmigrate.egg-info/entry_points.txt
tgmigrate.egg-info/not-zip-safe
tgmigrate.egg-info/paster_plugins.txt
tgmigrate.egg-info/requires.txt
tgmigrate.egg-info/sqlobject.txt
tgmigrate.egg-info/top_level.txt
