Metadata-Version: 1.0
Name: tgmigrate
Version: 0.2
Summary: sqlalchemy migrate command
Home-page: docs.turbogears.org
Author: Fred Lin
Author-email: gasolin+tg@gmail.com
License: UNKNOWN
Download-URL: http://www.python.org/pypi/tgmigrate/
Keywords: turbogears.command
Platform: UNKNOWN
Classifier: Development Status :: 3 - Alpha
Classifier: Operating System :: OS Independent
Classifier: Programming Language :: Python
Classifier: Topic :: Software Development :: Libraries :: Python Modules
Classifier: Framework :: TurboGears
